README.md
setup.py
dpnn_image/__init__.py
dpnn_image.egg-info/PKG-INFO
dpnn_image.egg-info/SOURCES.txt
dpnn_image.egg-info/dependency_links.txt
dpnn_image.egg-info/requires.txt
dpnn_image.egg-info/top_level.txt
dpnn_image/lib_py36/__init__.py
dpnn_image/lib_py36/dpnn_image.so
dpnn_image/lib_py36/libc.so.6
dpnn_image/lib_py36/libdl.so.2
dpnn_image/lib_py36/libgcc_s.so.1
dpnn_image/lib_py36/libm.so.6
dpnn_image/lib_py36/libpthread.so.0
dpnn_image/lib_py36/libpython3.6m.so.1.0
dpnn_image/lib_py36/librt.so.1
dpnn_image/lib_py36/libstdc++.so.6
dpnn_image/lib_py36/libutil.so.1
dpnn_image/lib_py38/__init__.py
dpnn_image/lib_py38/dpnn_image.so
dpnn_image/lib_py38/libc.so.6
dpnn_image/lib_py38/libdl.so.2
dpnn_image/lib_py38/libgcc_s.so.1
dpnn_image/lib_py38/libm.so.6
dpnn_image/lib_py38/libpthread.so.0
dpnn_image/lib_py38/libpython3.8.so.1.0
dpnn_image/lib_py38/librt.so.1
dpnn_image/lib_py38/libstdc++.so.6
dpnn_image/lib_py38/libutil.so.1
dpnn_image/lib_py39/__init__.py
dpnn_image/lib_py39/dpnn_image.so
dpnn_image/lib_py39/libc.so.6
dpnn_image/lib_py39/libdl.so.2
dpnn_image/lib_py39/libgcc_s.so.1
dpnn_image/lib_py39/libm.so.6
dpnn_image/lib_py39/libpthread.so.0
dpnn_image/lib_py39/libpython3.9.so.1.0
dpnn_image/lib_py39/librt.so.1
dpnn_image/lib_py39/libstdc++.so.6
dpnn_image/lib_py39/libutil.so.1
dpnn_image/test/__init__.py
dpnn_image/test/test_resize.py